README.md
pyproject.toml
setup.py
researches/__init__.py
researches/markdown.py
researches/primp.py
researches/primp.pyi
researches/schemas.py
researches/search.py
researches/utils.py
researches.egg-info/PKG-INFO
researches.egg-info/SOURCES.txt
researches.egg-info/dependency_links.txt
researches.egg-info/requires.txt
researches.egg-info/top_level.txt