Metadata-Version: 2.1
Name: researches
Version: 0.3
Summary: Researches is a Google search scraper.
Author-email: AWeirdDev <aweirdscratcher@gmail.com>
Project-URL: Source, https://github.com/AWeirdDev/researches
Project-URL: Bug Tracker, https://github.com/AWeirdDev/researches/issues
Keywords: google,search,scraper,research,llm
Classifier: Programming Language :: Python :: 3
Classifier: License :: OSI Approved :: MIT License
Classifier: Operating System :: OS Independent
Requires-Python: >=3.9
Requires-Dist: primp
Requires-Dist: selectolax
